{
    "status": 0, 
    "minitable": {
        "content": [
            [
                "a1", 
                "b1", 
                "c1"
            ], 
            [
                "a2", 
                "b2", 
                "c2"
            ]
        ], 
        "headers": [
            "A", 
            "B",
            "C"
        ], 
        "colwidth": [
            "40%", 
            "20%"
        ]
    }, 
    "description": "",
    "title": "",
    "filetype": "", 
    "filename": "",
    "iconfilename": "", 
    "readmefilename": "",
    "categorytitle": "",
    "species": "",
    "categoryid":""
}

